lib_llm/.DS_Store
lib_llm/__init__.py
lib_llm/gpt4/__init__.py
lib_llm/gpt4/extraction_chain.py
lib_llm/gpt4/schemas.py
lib_llm-0.1.0.dist-info/METADATA
lib_llm-0.1.0.dist-info/WHEEL
lib_llm-0.1.0.dist-info/RECORD
